UCTools/__init__.py
UCTools/upload.py
UCToolsZD-1.0.4.dist-info/METADATA
UCToolsZD-1.0.4.dist-info/WHEEL
UCToolsZD-1.0.4.dist-info/license.txt
UCToolsZD-1.0.4.dist-info/top_level.txt
UCToolsZD-1.0.4.dist-info/RECORD
