Metadata-Version: 2.1
Name: UCToolsZD
Version: 1.0.4
Summary: UCToolsZD
Author: xiejunwei
Author-email: xiejunwei@qq.com
License: MIT
Requires-Python: >=3
License-File: license.txt
Requires-Dist: pypinyin
Requires-Dist: opencv-python
